momics/__init__.py
momics/aggregate.py
momics/chromnn.py
momics/config.py
momics/dataset.py
momics/logging.py
momics/momics.py
momics/query.py
momics/streamer.py
momics/utils.py
momics/version.py
momics/cli/__init__.py
momics/cli/binnify.py
momics/cli/cli.py
momics/cli/cloudconfig.py
momics/cli/consolidate.py
momics/cli/cp.py
momics/cli/create.py
momics/cli/delete.py
momics/cli/ingest.py
momics/cli/ls.py
momics/cli/manifest.py
momics/cli/query.py
momics/cli/remove.py
momics/cli/tree.py
momics/cli/version.py
momics-0.4.0.dist-info/METADATA
momics-0.4.0.dist-info/WHEEL
momics-0.4.0.dist-info/entry_points.txt
momics-0.4.0.dist-info/licenses/LICENSE
momics-0.4.0.dist-info/RECORD
