Metadata-Version: 2.3
Name: momics
Version: 0.4.0
Summary: A package to create and manage genome-related TileDB arrays
Project-URL: homepage, https://js2264.github.io/momics
Project-URL: documentation, https://js2264.github.io/momics
Project-URL: repository, https://github.com/js2264/momics
Project-URL: changelog, https://github.com/js2264/momics/blob/devel/CHANGES.md
Author-email: Jacques Serizay <jacques.serizay@pasteur.fr>
License: CC BY-NC 4.0
License-File: LICENSE
Keywords: Tile-DB,bioinformatics,epigenomics,format,genomics,matrix,multi-omics,sparse
Classifier: Operating System :: OS Independent
Classifier: Programming Language :: Python :: 3
Requires-Python: >=3.8
Requires-Dist: biopython
Requires-Dist: click>=7
Requires-Dist: cloup
Requires-Dist: numpy
Requires-Dist: packaging
Requires-Dist: pandas
Requires-Dist: psutil
Requires-Dist: pyarrow>=1.0
Requires-Dist: pybigwig
Requires-Dist: pyfaidx
Requires-Dist: pyranges
Requires-Dist: setuptools
Requires-Dist: tensorflow[and-cuda]
Requires-Dist: tiledb
Requires-Dist: typing-extensions
Provides-Extra: all
Requires-Dist: biopython; extra == 'all'
Requires-Dist: dask[array,dataframe]; extra == 'all'
Requires-Dist: matplotlib; extra == 'all'
Requires-Dist: psutil; extra == 'all'
Provides-Extra: dev
Requires-Dist: biopython; extra == 'dev'
Requires-Dist: coverage[toml]; extra == 'dev'
Requires-Dist: dask[array,dataframe]; extra == 'dev'
Requires-Dist: isort; extra == 'dev'
Requires-Dist: matplotlib; extra == 'dev'
Requires-Dist: pre-commit; extra == 'dev'
Requires-Dist: psutil; extra == 'dev'
Requires-Dist: pytest; extra == 'dev'
Requires-Dist: pytest-cov; extra == 'dev'
Requires-Dist: pytest-order; extra == 'dev'
Requires-Dist: python-dotenv; extra == 'dev'
Requires-Dist: ruff; extra == 'dev'
Requires-Dist: twine; extra == 'dev'
Provides-Extra: docs
Requires-Dist: autodoc; extra == 'docs'
Requires-Dist: autodocsumm; extra == 'docs'
Requires-Dist: furo; extra == 'docs'
Requires-Dist: lxml[html-clean]; extra == 'docs'
Requires-Dist: m2r; extra == 'docs'
Requires-Dist: myst-parser; extra == 'docs'
Requires-Dist: nbsphinx; extra == 'docs'
Requires-Dist: pydata-sphinx-theme; extra == 'docs'
Requires-Dist: recommonmark; extra == 'docs'
Requires-Dist: sphinx-autoapi; extra == 'docs'
Requires-Dist: sphinx-autobuild; extra == 'docs'
Requires-Dist: sphinx-click; extra == 'docs'
Requires-Dist: sphinx-rtd-theme; extra == 'docs'
Requires-Dist: sphinx>=1.6; extra == 'docs'
Requires-Dist: sphinxcontrib-napoleon; extra == 'docs'
Provides-Extra: test
Requires-Dist: coverage[toml]; extra == 'test'
Requires-Dist: isort; extra == 'test'
Requires-Dist: pytest; extra == 'test'
Requires-Dist: pytest-cov; extra == 'test'
Requires-Dist: pytest-order; extra == 'test'
Requires-Dist: python-dotenv; extra == 'test'
Requires-Dist: ruff; extra == 'test'
